fawaris_fastapi/__init__.py
fawaris_fastapi/exception_handlers.py
fawaris_fastapi/exceptions.py
fawaris_fastapi/main.py
fawaris_fastapi/scripts/create_tables.py
fawaris_fastapi/scripts/task_all.py
fawaris_fastapi/sep10.py
fawaris_fastapi/sep24.py
fawaris_fastapi/settings.py
fawaris_fastapi/tables.py
fawaris_fastapi/utils.py
fawaris_fastapi-0.1.1.dist-info/WHEEL
fawaris_fastapi-0.1.1.dist-info/METADATA
fawaris_fastapi-0.1.1.dist-info/RECORD
